<?xml version="1.0" encoding="utf-8"?>
<LanguageData>

<MM_AchievementMagicHunter.label>Chasseur magique</MM_AchievementMagicHunter.label>
<MM_AchievementMagicHunter.description>Tuer n'importe quelle créature magique du projet Hécate.</MM_AchievementMagicHunter.description>

<MM_AchievementStayingAhead.label>Encore une tête !</MM_AchievementStayingAhead.label>
<MM_AchievementStayingAhead.description>Tuer 5 Hydres de Lerne.</MM_AchievementStayingAhead.description>

<MM_AchievementHardLove.label>Amour difficile</MM_AchievementHardLove.label>
<MM_AchievementHardLove.description>Faites en sorte qu'un colon développe un lien avec un catoblépas.</MM_AchievementHardLove.description>

<MM_AchievementMagicParka.label>Parka magique</MM_AchievementMagicParka.label>
<MM_AchievementMagicParka.description>Fabriquer une parka en cuir lourd magique.</MM_AchievementMagicParka.description>

<MM_AchievementGrabbingHands.label>Saisir sa main</MM_AchievementGrabbingHands.label>
<MM_AchievementGrabbingHands.description>Faire en sorte qu'un colon soit saisi par un Ahuizotl.</MM_AchievementGrabbingHands.description>

<MM_AchievementFountainOfBlood.label>Fontaine de sang</MM_AchievementFountainOfBlood.label>
<MM_AchievementFountainOfBlood.description>Faire en sorte qu'un colon soit affecté par une blessure hémorragique.</MM_AchievementFountainOfBlood.description>

<MM_AchievementStatueOfColonist.label>Statue d'un colon</MM_AchievementStatueOfColonist.label>
<MM_AchievementStatueOfColonist.description>Faire mourir un colon ou un animal de la pétrification.</MM_AchievementStatueOfColonist.description>

<MM_AchievementForbiddenPoultry.label>Volaille interdite</MM_AchievementForbiddenPoultry.label>
<MM_AchievementForbiddenPoultry.description>Utiliser un œuf de griffon fécondé pour cuisiner un plat gastronomique.</MM_AchievementForbiddenPoultry.description>


</LanguageData>