<?xml version="1.0" encoding="utf-8"?>
<LanguageData>

		<!-- +++++ Building +++++ -->
<comfierThanUsual.label>Plus confortable que d'habitude</comfierThanUsual.label>
<comfierThanUsual.description>Construire un fauteuil en cuir humain.</comfierThanUsual.description>

<theArchitect.label>L'architecte</theArchitect.label>
<theArchitect.description>Construire 1 000 murs.</theArchitect.description>

<buildingTheSkynet.label>Construire Skynet</buildingTheSkynet.label>
<buildingTheSkynet.description>Construire 30 mini-tourelles.</buildingTheSkynet.description>

<itAintRocketScience.label>Ce n'est pas sorcier</itAintRocketScience.label>
<itAintRocketScience.description>Construire un vaisseau spatial.</itAintRocketScience.description>

		<!-- +++++ ColonistCount +++++ -->
<iWillSurvive.label>Je vais survivre</iWillSurvive.label>
<iWillSurvive.description>Avoir 7 colons.</iWillSurvive.description>

<imStillStanding.label>Je suis toujours debout</imStillStanding.label>
<imStillStanding.description>Avoir 12 colons.</imStillStanding.description>

<imASurvivor.label>Je suis un survivant</imASurvivor.label>
<imASurvivor.description>Avoir 18 colons.</imASurvivor.description>

<aintNoStoppingUsNow.label>Rien ne nous arrêtera</aintNoStoppingUsNow.label>
<aintNoStoppingUsNow.description>Avoir 33 colons.</aintNoStoppingUsNow.description>

		<!-- +++++ Hediffs +++++ -->
<T-800.label>T-800</T-800.label>
<T-800.description>Avoir un colon avec les jambes, les bras, une colonne vertébrale, les oreilles et les yeux bioniques.</T-800.description>

<imAPirate.label>Je suis un pirate !</imAPirate.label>
<imAPirate.description>Installer une jambe de bois sur un colon.</imAPirate.description>

<thatllShowHim.label>Ça lui apprendra</thatllShowHim.label>
<thatllShowHim.description>Affamer un colon à mort.</thatllShowHim.description>

		<!-- +++++ Incidents +++++ -->
<thisIsWhereTheFunBegins.label>C'est ici que le plaisir commence</thisIsWhereTheFunBegins.label>
<thisIsWhereTheFunBegins.description>Subir un raid pour la première fois.</thisIsWhereTheFunBegins.description>

<showMustGoOn.label>Le spectacle doit continuer</showMustGoOn.label>
<showMustGoOn.description>Demander à l'homme en noir de rejoindre votre colonie.</showMustGoOn.description>

<brrr.label>Gla-gla</brrr.label>
<brrr.description>Avoir une vague de froid en hiver.</brrr.description>

<phew.label>Pfiou !</phew.label>
<phew.description>Avoir une vague de chaleur en été.</phew.description>

<outOfTheFryingPan.label>Hors de la poêle</outOfTheFryingPan.label>
<outOfTheFryingPan.description>Demander à un colon de développer un lien avec un cochon.</outOfTheFryingPan.description>

<intoTheFire.label>Dans le feu</intoTheFire.label>
<intoTheFire.description>Tuer un cochon avec un lien dans le feu.</intoTheFire.description>

<blitzkrieg.label>Guerre éclair</blitzkrieg.label>
<blitzkrieg.description>Détruire 5 bases de factions.</blitzkrieg.description>

		<!-- +++++ Items +++++ -->
<oneStepCloser.label>Un pas de plus</oneStepCloser.label>
<oneStepCloser.description>Obtenir un noyau IA de personnalité.</oneStepCloser.description>

<humanLeatherHat.label>Chapeau de cow-boy en cuir humain</humanLeatherHat.label>
<humanLeatherHat.description>Fabriquer un chapeau de cow-boy en cuir humain.</humanLeatherHat.description>

<midas.label>Midas</midas.label>
<midas.description>Avoir 5 000 d'or.</midas.description>

<fourtwentyblazeIt.label>4/20 Brûlez-le</fourtwentyblazeIt.label>
<fourtwentyblazeIt.description>Obtenir 420 feuilles de smokeleaf</fourtwentyblazeIt.description>

<silenceOfTheLambs.label>Le silence des agneaux</silenceOfTheLambs.label>
<silenceOfTheLambs.description>Obtenir 100 viandes humaines.</silenceOfTheLambs.description>

<theStuffOfLegends.label>Équipement légendaire</theStuffOfLegends.label>
<theStuffOfLegends.description>Fabriquer un objet de qualité légendaire.</theStuffOfLegends.description>

<futureCaveman.label>L'homme des cavernes du futur</futureCaveman.label>
<futureCaveman.description>Fabriquer une massue en plastacier.</futureCaveman.description>

		<!-- +++++ Kills +++++ -->
<firstBlood.label>Premier sang</firstBlood.label>
<firstBlood.description>Tuer un autre colon.</firstBlood.description>

<bloodlust.label>Soif de sang</bloodlust.label>
<bloodlust.description>Tuer un total de 100 humains.</bloodlust.description>

<bloodForTheBloodGod.label>Du sang pour le Dieu du sang</bloodForTheBloodGod.label>
<bloodForTheBloodGod.description>Tuer un total de 1 000 humains.</bloodForTheBloodGod.description>

<bigGameHunter.label>Chasseur de gros gibier</bigGameHunter.label>
<bigGameHunter.description>Chasser et tuer 20 thrumbos.</bigGameHunter.description>

<exterminator.label>Exterminateur</exterminator.label>
<exterminator.description>Tuer 150 insectoïdes.</exterminator.description>

<dragonSlayer.label>Tueur de dragon</dragonSlayer.label>
<dragonSlayer.description>Tuer 50 iguanes.</dragonSlayer.description>

<australianRevenge.label>Vengeance australienne</australianRevenge.label>
<australianRevenge.description>Tuer 30 émeus.</australianRevenge.description>

		<!-- +++++ Livestock +++++ -->
<threeLittlePigs.label>Les trois petits cochons</threeLittlePigs.label>
<threeLittlePigs.description>Avoir 3 cochons et 1 loup des bois.</threeLittlePigs.description>

<lookAtAllThoseChickens.label>Regarder tous ces poulets</lookAtAllThoseChickens.label>
<lookAtAllThoseChickens.description>Avoir 20 oies.</lookAtAllThoseChickens.description>

<sustainableFuelSource.label>Source de carburant durable</sustainableFuelSource.label>
<sustainableFuelSource.description>Avoir 8 boomalopes.</sustainableFuelSource.description>

<muffaloRancher.label>Éleveur de muffalo</muffaloRancher.label>
<muffaloRancher.description>Avoir 12 muffalos.</muffaloRancher.description>

<arkHalfFull.label>Arche à moitié pleine</arkHalfFull.label>
<arkHalfFull.description>Avoir les 58 animaux du jeu de base en même temps.</arkHalfFull.description>

<gentleGiant.label>Géant doux</gentleGiant.label>
<gentleGiant.description>Apprivoiser un thrumbo.</gentleGiant.description>

		<!-- +++++ MentalBreaks +++++ -->
<aFormalComplaint.label>Une plainte formelle</aFormalComplaint.label>
<aFormalComplaint.description>Avoir un colon fou furieux.</aFormalComplaint.description>

<callOfTheWild.label>L'appel de la nature</callOfTheWild.label>
<callOfTheWild.description>Avoir un colon sauvage.</callOfTheWild.description>

<letsStartARevolution.label>Commençons la révolution</letsStartARevolution.label>
<letsStartARevolution.description>Avoir 5 colons dans un état mental en même temps.</letsStartARevolution.description>

<fiftyShadesOfGrey.label>50 nuances de Grey</fiftyShadesOfGrey.label>
<fiftyShadesOfGrey.description>Avoir un colon dans une rage sadique attaquer un prisonnier.</fiftyShadesOfGrey.description>

		<!-- +++++ Mood +++++ -->
<aHappyEnding.label>Fin heureuse</aHappyEnding.label>
<aHappyEnding.description>Avoir une humeur moyenne de 90% dans votre colonie.</aHappyEnding.description>

<areYouNotEntertained.label>Vous ne vous amusez pas ?</areYouNotEntertained.label>
<areYouNotEntertained.description>Avoir une humeur moyenne de 5% dans votre colonie.</areYouNotEntertained.description>

		<!-- +++++ Quests +++++ -->
<mercenary.label>Mercenaire</mercenary.label>
<mercenary.description>Terminer 5 quêtes.</mercenary.description>

<ambassadorOfPeace.label>Ambassadeur de paix</ambassadorOfPeace.label>
<ambassadorOfPeace.description>Terminer 3 quêtes de pourparlers de paix.</ambassadorOfPeace.description>

		<!-- +++++ Records +++++ -->
<OneShotOneKill.label>Un tir, un mort</OneShotOneKill.label>
<OneShotOneKill.description>Avoir un colon avec 100 tirs dans la tête.</OneShotOneKill.description>

<TriggerHappy.label>Gâchette facile</TriggerHappy.label>
<TriggerHappy.description>Avoir un colon avec 2 000 coups de feu tirés.</TriggerHappy.description>

<OneSolidGardner.label>Un vrai jardinier</OneSolidGardner.label>
<OneSolidGardner.description>Avoir un colon avec 10 000 plantes semées.</OneSolidGardner.description>

<LifeSentence.label>Condamnation à perpétuité</LifeSentence.label>
<LifeSentence.description>Avoir le même prisonnier pendant 2 ans.</LifeSentence.description>

<IMightNeedAShrink.label>J'ai peut-être besoin d'un psy</IMightNeedAShrink.label>
<IMightNeedAShrink.description>Avoir un colon avec un total de 24 heures d’état mental.</IMightNeedAShrink.description>

<DrDolittle.label>Dr. Dolittle</DrDolittle.label>
<DrDolittle.description>Avoir un colon avec 50 animaux apprivoisés.</DrDolittle.description>

<ProfessionalStripper.label>Strip-teaseur professionnel</ProfessionalStripper.label>
<ProfessionalStripper.description>Avoir un colon avec 100 corps dépouillés.</ProfessionalStripper.description>

<BladeRunner.label>Blade Runner</BladeRunner.label>
<BladeRunner.description>Avoir un colon avec 50 mécanoïdes abattus.</BladeRunner.description>

<ThreeStarMichelin.label>3 étoiles au Michelin</ThreeStarMichelin.label>
<ThreeStarMichelin.description>Avoir un colon avec 10 000 repas cuisinés.</ThreeStarMichelin.description>

<ScrubUp.label>Se laver les mains</ScrubUp.label>
<ScrubUp.description>Réaliser un total de 50 opérations médicales.</ScrubUp.description>

<TheRimsBrightest.label>Le plus brillant de la Bordure</TheRimsBrightest.label>
<TheRimsBrightest.description>Consacrer un total de 2 ans à la recherche.</TheRimsBrightest.description>

<IWishThisWasIkea.label>J'aimerais que ce soit du IKEA</IWishThisWasIkea.label>
<IWishThisWasIkea.description>Construire ET démonter un total de 100 structures.</IWishThisWasIkea.description>

<ImOnFire.label>Je suis en feu !</ImOnFire.label>
<ImOnFire.description>Avoir un colon avec un total de 3 jours en feu.</ImOnFire.description>

		<!-- +++++ Research +++++ -->
<sticksAndStones.label>Bâtons et pierres</sticksAndStones.label>
<sticksAndStones.description>Rechercher toutes les technologies néolithiques.</sticksAndStones.description>

<outOfTheDarkAges.label>Sortir de l'âge sombre</outOfTheDarkAges.label>
<outOfTheDarkAges.description>Rechercher toutes les technologies médiévales.</outOfTheDarkAges.description>

<industrialRevolution.label>Révolution industrielle</industrialRevolution.label>
<industrialRevolution.description>Recherche de toutes les technologies industrielles.</industrialRevolution.description>

<offToTheStars.label>En route vers les étoiles</offToTheStars.label>
<offToTheStars.description>Rechercher toutes les technologies spatiales.</offToTheStars.description>

		<!-- +++++ Skills +++++ -->
<sharpshooter.label>Tireur d'élite</sharpshooter.label>
<sharpshooter.description>Avoir un colon qui atteint le niveau 20 en tir.</sharpshooter.description>

<mrPresident.label>M. le Président</mrPresident.label>
<mrPresident.description>Avoir un colon qui atteint le niveau 20 en sociabilité.</mrPresident.description>

<conanTheBarbarian.label>Crom dieu barbare</conanTheBarbarian.label>
<conanTheBarbarian.description>Avoir un colon qui atteint le niveau 20 en mêlée.</conanTheBarbarian.description>

		<!-- +++++ Time +++++ -->
<couldBeWorse.label>Ça pourrait être pire</couldBeWorse.label>
<couldBeWorse.description>Survivre une saison.</couldBeWorse.description>

<itsAllDownhillFromHere.label>C'est tout en descente à partir d'ici</itsAllDownhillFromHere.label>
<itsAllDownhillFromHere.description>Survivre un an.</itsAllDownhillFromHere.description>

<tenHoursWoah.label>10 heures ? Woah !</tenHoursWoah.label>
<tenHoursWoah.description>Consacrer 10 heures à jouer la colonie actuelle.</tenHoursWoah.description>

<waitAMinute.label>Attendez une minute !</waitAMinute.label>
<waitAMinute.description>Consacrer 100 heures à jouer la colonie actuelle.</waitAMinute.description>

		<!-- +++++ Trade +++++ -->
<pabloEmilioEscobarGaviria.label>Pablo Emilio Escobar Gaviria</pabloEmilioEscobarGaviria.label>
<pabloEmilioEscobarGaviria.description>Offrir 400 yayo à un seul négociant et en une seule transaction.</pabloEmilioEscobarGaviria.description>

<wolfOfWallStreet.label>Le Loup de Wall Street</wolfOfWallStreet.label>
<wolfOfWallStreet.description>Gagner 3 000 d'argent en une seule transaction.</wolfOfWallStreet.description>

<slaverScum.label>Ordure d'esclavagiste</slaverScum.label>
<slaverScum.description>Offrir 5 prisonniers en une seule transaction.</slaverScum.description>

		<!-- +++++ Wealth +++++ -->
<inForAPenny.label>Pour un centime</inForAPenny.label>
<inForAPenny.description>Accumuler une richesse de colonie de 100 000.</inForAPenny.description>

<inForAPound.label>Pour une pièce</inForAPound.label>
<inForAPound.description>Accumuler une richesse de colonie de 1 000 000.</inForAPound.description>


<!-- v1.5 -->
<VAE_Multiculture.label>Multiculturel</VAE_Multiculture.label>
<VAE_Multiculture.description>Avoir au moins 4 idéoligions différentes dans votre colonie.</VAE_Multiculture.description>

<VAE_SlaveOwner.label>Propriétaire d'esclave</VAE_SlaveOwner.label>
<VAE_SlaveOwner.description>Réduire une personne en esclavage.</VAE_SlaveOwner.description>

<VAE_SlaveDriver.label>Conducteur d'esclaves</VAE_SlaveDriver.label>
<VAE_SlaveDriver.description>Posséder 5 esclaves en même temps.</VAE_SlaveDriver.description>

<VAE_HappyTreeCritters.label>Joyeuses créatures des arbres</VAE_HappyTreeCritters.label>
<VAE_HappyTreeCritters.description>Obtenir 15 dryades peau d'écorce.</VAE_HappyTreeCritters.description>

<VAE_Bloodsuckers.label>Suceurs de sang</VAE_Bloodsuckers.label>
<VAE_Bloodsuckers.description>Avoir 3 colons avec le gène hémogénique.</VAE_Bloodsuckers.description>

<VAE_NeedMoreCatgirls.label>Besoin de plus de filles-chats</VAE_NeedMoreCatgirls.label>
<VAE_NeedMoreCatgirls.description>Avoir 3 psycharmeurs dans la même colonie.</VAE_NeedMoreCatgirls.description>

<VAE_UngusAndBungus.label>Ungus et Bungus</VAE_UngusAndBungus.label>
<VAE_UngusAndBungus.description>Avoir une colonie avec 10 néandertaliens.</VAE_UngusAndBungus.description>

<VAE_AMachineForPigs.label>Une machine pour les cochons</VAE_AMachineForPigs.label>
<VAE_AMachineForPigs.description>Tuer 100 hommes-cochons.</VAE_AMachineForPigs.description>

<VAE_MeltingPot.label>Creuset</VAE_MeltingPot.label>
<VAE_MeltingPot.description>Obtenir un colon de chaque xénotype (jeu de base).</VAE_MeltingPot.description>

<VAE_NewGeneration.label>Nouvelle génération</VAE_NewGeneration.label>
<VAE_NewGeneration.description>Avoir 10 naissances naturelles dans la colonie.</VAE_NewGeneration.description>

<VAE_GetAGhoul.label>Ne la laissez pas s'affamer</VAE_GetAGhoul.label>
<VAE_GetAGhoul.description>Avoir une goule.</VAE_GetAGhoul.description>

<VAE_ContainARevenant.label>Lâche invisible</VAE_ContainARevenant.label>
<VAE_ContainARevenant.description>Confiner un revenant.</VAE_ContainARevenant.description>

<VAE_Nananana.label>Na-na-na-na</VAE_Nananana.label>
<VAE_Nananana.description>Confiner une nociosphère.</VAE_Nananana.description>

<VAE_PrinceOfAllCosmos.label>Prince de tout le cosmos</VAE_PrinceOfAllCosmos.label>
<VAE_PrinceOfAllCosmos.description>Activer une nociosphère.</VAE_PrinceOfAllCosmos.description>

<VAE_ItsDangerouslyDangerous.label>Dangereusement dangereux</VAE_ItsDangerouslyDangerous.label>
<VAE_ItsDangerouslyDangerous.description>Activer 5 nociosphères.</VAE_ItsDangerouslyDangerous.description>

<VAE_PurePerfection.label>La perfection à l'état pur</VAE_PurePerfection.label>
<VAE_PurePerfection.description>Confiner un cube doré. Aimer le cube.</VAE_PurePerfection.description>

<VAE_PlatonicSolid.label>Solide et platonique</VAE_PlatonicSolid.label>
<VAE_PlatonicSolid.description>Avoir 7 colons qui ont de l'intérêt pour le cube.</VAE_PlatonicSolid.description>

<VAE_TheNightParty.label>La fête nocturne</VAE_TheNightParty.label>
<VAE_TheNightParty.description>Confiner 2 noctols et 2 occulteurs.</VAE_TheNightParty.description>

<VAE_EmbraceTheVoid.label>Embrasser le néant</VAE_EmbraceTheVoid.label>
<VAE_EmbraceTheVoid.description>Demander à un colon d'embrasser le néant.</VAE_EmbraceTheVoid.description>

<VAE_BlindedByTheLight.label>Aveuglé par la lumière</VAE_BlindedByTheLight.label>
<VAE_BlindedByTheLight.description>Étourdir un ennemi à l'aide d'une fusée disruptive.</VAE_BlindedByTheLight.description>

<VAE_SecureContainProtect.label>Sécuriser, contenir, protéger</VAE_SecureContainProtect.label>
<VAE_SecureContainProtect.description>Avoir un total de 30 entités confinées.</VAE_SecureContainProtect.description>

<VAE_OriginalityIsDead.label>L'original est mort</VAE_OriginalityIsDead.label>
<VAE_OriginalityIsDead.description>Avoir au moins 10 personnes dupliquées.</VAE_OriginalityIsDead.description>

<VAE_Witcher.label>The Witcher</VAE_Witcher.label>
<VAE_Witcher.description>Tuer un revenant avec une épée longue.</VAE_Witcher.description>

<VAE_WarAgainstTheMachines.label>Guerre contre les machines</VAE_WarAgainstTheMachines.label>
<VAE_WarAgainstTheMachines.description>Vaincre un groupe de mécanoïdes.</VAE_WarAgainstTheMachines.description>

<VAE_MachinesFromTheFuture.label>Machines venues du futur</VAE_MachinesFromTheFuture.label>
<VAE_MachinesFromTheFuture.description>Vaincre 5 groupes de mécanoïdes.</VAE_MachinesFromTheFuture.description>

<VAE_UnstableCells.label>N'exploseront certainement pas</VAE_UnstableCells.label>
<VAE_UnstableCells.description>Récupérer 5 cellules de puissance instable.</VAE_UnstableCells.description>

<VAE_NotInMyBackyard.label>Pas dans ma cour</VAE_NotInMyBackyard.label>
<VAE_NotInMyBackyard.description>Terminer avec succès une quête cause du problème.</VAE_NotInMyBackyard.description>

<VAE_BlueBlood.label>Sang bleu</VAE_BlueBlood.label>
<VAE_BlueBlood.description>Avoir un colon avec le titre propriétaire foncier de l'Empire.</VAE_BlueBlood.description>

<VAE_NobleDeeds.label>Acte noble</VAE_NobleDeeds.label>
<VAE_NobleDeeds.description>Avoir 3 colons avec le titre écuyer/écuyère de l'Empire.</VAE_NobleDeeds.description>

<VAE_UpTheRanks.label>Monter en grade</VAE_UpTheRanks.label>
<VAE_UpTheRanks.description>Avoir un colon avec le titre chevalier/chevaleresse de l'Empire.</VAE_UpTheRanks.description>

<VAE_EnlightenedAristocracy.label>Aristocratie éclairée</VAE_EnlightenedAristocracy.label>
<VAE_EnlightenedAristocracy.description>Avoir un colon avec le titre comte/comtesse de l'Empire.</VAE_EnlightenedAristocracy.description>

<VAE_TheRoyalCourt.label>La Cour royale</VAE_TheRoyalCourt.label>
<VAE_TheRoyalCourt.description>Avoir au moins 5 colons avec le titre chevalier/chevaleresse ou plus.</VAE_TheRoyalCourt.description>

<VAE_RoyalArms.label>Armes royales</VAE_RoyalArms.label>
<VAE_RoyalArms.description>Récupérer une épée mono-moléculaire, un marteau de Zeus et une épée plasmique (non consciente).</VAE_RoyalArms.description>

<VAE_AnimaTorture.label>Torture Anima</VAE_AnimaTorture.label>
<VAE_AnimaTorture.description>Abattre 5 arbres anima, au mépris des hurlements.</VAE_AnimaTorture.description>

<VAE_IceCold.label>Froid glacial</VAE_IceCold.label>
<VAE_IceCold.description>Demander à vos colons de consommer 100 bières.</VAE_IceCold.description>

<VAE_Munchies.label>Grignotage</VAE_Munchies.label>
<VAE_Munchies.description>Demander à vos colons de manger 100 plats gastronomiques (ni végétariens,  ni carnivores).</VAE_Munchies.description>

<VAE_TastesLikePeanuts.label>Goût de cacahuètes</VAE_TastesLikePeanuts.label>
<VAE_TastesLikePeanuts.description>Demander à vos colons de manger 100 plats contenant de la viande d'insecte.</VAE_TastesLikePeanuts.description>

<VAE_NoEnergyNoTown.label>Pas d'énergie, pas de ville</VAE_NoEnergyNoTown.label>
<VAE_NoEnergyNoTown.description>Demander à des cochons ou à des sangliers de se nourrir 100 fois de cadavres.</VAE_NoEnergyNoTown.description>

<VAE_TheOtherPig.label>Porc d'iran</VAE_TheOtherPig.label>
<VAE_TheOtherPig.description>Demander à vos colons de commettre 50 fois des actes de cannibalisme.</VAE_TheOtherPig.description>

<VAE_CaptainPlanetWouldGetAStroke.label>Captain Planet aurait une attaque</VAE_CaptainPlanetWouldGetAStroke.label>
<VAE_CaptainPlanetWouldGetAStroke.description>Demander à votre animal de compagnie, le thrumbos, de consommer 50 arbres.</VAE_CaptainPlanetWouldGetAStroke.description>

<VAE_MidasTouch.label>Le toucher de Midas</VAE_MidasTouch.label>
<VAE_MidasTouch.description>Fabriquer un objet en or de qualité excellente ou supérieure.</VAE_MidasTouch.description>

<VAE_TacticalNukeInbound.label>Lancement nucléaire détecté</VAE_TacticalNukeInbound.label>
<VAE_TacticalNukeInbound.description>Tuer un humain avec un lance-roquettes apocalyptique.</VAE_TacticalNukeInbound.description>

<VAE_TakeThatMickey.label>Prends ça, Mickey</VAE_TakeThatMickey.label>
<VAE_TakeThatMickey.description>Avoir un rat qui meurt dans un piège à pointes.</VAE_TakeThatMickey.description>

<VAE_BabysFirstMods.label>Premiers mods de bébé</VAE_BabysFirstMods.label>
<VAE_BabysFirstMods.description>Avoir 10 mods actifs dans la liste de mods.</VAE_BabysFirstMods.description>

<VAE_NoRedErrors.label>Aucune erreur rouge</VAE_NoRedErrors.label>
<VAE_NoRedErrors.description>Avoir 100 mods actifs dans la liste de mods.</VAE_NoRedErrors.description>

<VAE_TheyAreAllQoL.label>Que pour la qualité de vie !</VAE_TheyAreAllQoL.label>
<VAE_TheyAreAllQoL.description>Avoir 500 mods actifs dans la liste de mods.</VAE_TheyAreAllQoL.description>

<VAE_FirstHarvest.label>Première récolte</VAE_FirstHarvest.label>
<VAE_FirstHarvest.description>Récolter 50 plants de maïs.</VAE_FirstHarvest.description>

<VAE_FinestCloth.label>Tissu de qualité</VAE_FinestCloth.label>
<VAE_FinestCloth.description>Récolter 100 plants de diabledeau.</VAE_FinestCloth.description>

<VAE_FreedomDenied.label>Liberté refusée</VAE_FreedomDenied.label>
<VAE_FreedomDenied.description>Avoir son premier prisonnier.</VAE_FreedomDenied.description>

<VAE_RuraPenthe.label>Fox River</VAE_RuraPenthe.label>
<VAE_RuraPenthe.description>Avoir 10 prisonniers en même temps.</VAE_RuraPenthe.description>

<VAE_PrisonArchitect.label>Prison Architect</VAE_PrisonArchitect.label>
<VAE_PrisonArchitect.description>Capturer 100 prisonniers (cumulatif).</VAE_PrisonArchitect.description>

<VAE_PlantsVsZombies.label>Plantes Vs Zombies</VAE_PlantsVsZombies.label>
<VAE_PlantsVsZombies.description>Demander à une dryade griffe de tuer un assaillant zombie.</VAE_PlantsVsZombies.description>

<VAE_ItBelongsInAMuseum.label>Sa place est dans un musée</VAE_ItBelongsInAMuseum.label>
<VAE_ItBelongsInAMuseum.description>Obtenir 3 reliques.</VAE_ItBelongsInAMuseum.description>

<VAE_Wololo.label>Wololo</VAE_Wololo.label>
<VAE_Wololo.description>Utiliser 10 fois la capacité &lt;color=#ffea68&gt;convertir&lt;/color&gt; de votre guide spirituel.</VAE_Wololo.description>

<VAE_UpsyDaisyVampireyHealyPower.label>Soins vampiriques</VAE_UpsyDaisyVampireyHealyPower.label>
<VAE_UpsyDaisyVampireyHealyPower.description>Utiliser au moins 20 fois la capacité &lt;color=#ffea68&gt;coagulation&lt;/color&gt;.</VAE_UpsyDaisyVampireyHealyPower.description>

<VAE_StokingTheFire.label>Attiser le feu</VAE_StokingTheFire.label>
<VAE_StokingTheFire.description>Utiliser la capacité &lt;color=#ffea68&gt;crache feu&lt;/color&gt; sur une cible déjà en feu.</VAE_StokingTheFire.description>

<VAE_SpineOverkill.label>Épine démesurée</VAE_SpineOverkill.label>
<VAE_SpineOverkill.description>Utiliser la capacité &lt;color=#ffea68&gt;épine perçante&lt;/color&gt; sur une cible ayant moins de 5% de points de vie.</VAE_SpineOverkill.description>

<VAE_YouAndWhoseArmy.label>Toi et l'armée de qui ?</VAE_YouAndWhoseArmy.label>
<VAE_YouAndWhoseArmy.description>Utiliser 10 fois la capacité &lt;color=#ffea68&gt;appel de guerre des animaux&lt;/color&gt; pour invoquer des créatures sauvages.</VAE_YouAndWhoseArmy.description>

<VAE_JustASippy.label>Juste une gorgée</VAE_JustASippy.label>
<VAE_JustASippy.description>Utilisez la capacité &lt;color=#ffea68&gt;alimentation sanguine&lt;/color&gt; sur une cible amicale.</VAE_JustASippy.description>

<VAE_MeatForTheGrinder.label>De la viande pour le broyeur</VAE_MeatForTheGrinder.label>
<VAE_MeatForTheGrinder.description>Utiliser la capacité &lt;color=#ffea68&gt;massacre psychique&lt;/color&gt; pour transformer un tribal en un tas de viande informe.</VAE_MeatForTheGrinder.description>

<VAE_SorcererSupreme.label>Sorcier suprême</VAE_SorcererSupreme.label>
<VAE_SorcererSupreme.description>Avoir un colon avec 10 psysorts.</VAE_SorcererSupreme.description>

<VAE_SecondWind.label>Second souffle</VAE_SecondWind.label>
<VAE_SecondWind.description>Utiliser &lt;color=#ffea68&gt;inhibition de la douleur&lt;/color&gt; sur un colon dont l'état de santé est inférieur à 20% pour le ramener au combat... et risquer de le voir mourir.</VAE_SecondWind.description>

<VAE_WhoaBack.label>Retour au calme</VAE_WhoaBack.label>
<VAE_WhoaBack.description>Utiliser &lt;color=#ffea68&gt;étourdissement&lt;/color&gt; sur un thrumbo chasseur d'hommes</VAE_WhoaBack.description>

<VAE_EpilepticSeizure.label>Crise épileptique</VAE_EpilepticSeizure.label>
<VAE_EpilepticSeizure.description>Avoir un colon qui a utilisé 10 fois &lt;color=#ffea68&gt;tremblement psychique&lt;/color&gt;.</VAE_EpilepticSeizure.description>

<VAE_VeryCapable.label>Très compétent</VAE_VeryCapable.label>
<VAE_VeryCapable.description>Obtenir un total de 100 capacités sur l'ensemble de vos colons. Mode difficile : sans DLC ni mods (impossible).</VAE_VeryCapable.description>


</LanguageData>