<?xml version="1.0" encoding="utf-8"?>
<LanguageData>

<VFEE_IngestedAperitif.label>apéritif ingéré</VFEE_IngestedAperitif.label>
<VFEE_IngestedAperitif.description>Protection contre les infections et le poison dans l'estomac, ainsi que la possibilité de consommer des repas supplémentaires pour une meilleure amélioration de l'humeur.</VFEE_IngestedAperitif.description>
<VFEE_IngestedAperitif.labelNoun>une ingestion d'apéritif</VFEE_IngestedAperitif.labelNoun>

<VFEE_AcidifierFletcher.label>acidifiant</VFEE_AcidifierFletcher.label>
<VFEE_AcidifierFletcher.description>Mélange acidifiant injecté dans les veines par une fléchette. Provoque une douleur extrême et une mort quasi instantanée par brûlure interne à l'acide.</VFEE_AcidifierFletcher.description>

<VFEE_AcidifierToxblade.label>acidifiant</VFEE_AcidifierToxblade.label>
<VFEE_AcidifierToxblade.description>Mélange acidifiant injecté dans les veines par une fléchette. Provoque une douleur extrême et une mort quasi instantanée par brûlure interne à l'acide.</VFEE_AcidifierToxblade.description>


</LanguageData>