<?xml version="1.0" encoding="utf-8"?>
<LanguageData>

<VAECaves_AncientGiantSpider.label>ancienne araignée géante</VAECaves_AncientGiantSpider.label>

<VAECaves_BlindSalamander.label>salamandre aveugle</VAECaves_BlindSalamander.label>

<VAECaves_CaveBear.label>ours des cavernes</VAECaves_CaveBear.label>

<VAECaves_CaveCrawler.label>chenille des cavernes</VAECaves_CaveCrawler.label>

<VAECaves_GiantSpider.label>araignée géante</VAECaves_GiantSpider.label>

<VAECaves_GiantSpiderHatchling.label>araignée géante éclosion</VAECaves_GiantSpiderHatchling.label>

<VAECaves_InsectoidHulk.label>brute insectoïde</VAECaves_InsectoidHulk.label>

<VAECaves_Wyrm.label>wyrm</VAECaves_Wyrm.label>


</LanguageData>