<?xml version="1.0" encoding="utf-8"?>
<LanguageData>

  <VEE_Plant_Bluebell.label>jacinthe</VEE_Plant_Bluebell.label>
  <VEE_Plant_Bluebell.description>Une fleur de jardin à la teinte bleu-violet, aux pétales fortement recourbés. Les jacinthes sont très belles et durent longtemps.</VEE_Plant_Bluebell.description>

  <VEE_Plant_Gardenia.label>gardénia</VEE_Plant_Gardenia.label>
  <VEE_Plant_Gardenia.description>Une fleur à grands pétales. Les gardénias sont très jolies.</VEE_Plant_Gardenia.description>

  <VEE_Plant_Gentian.label>gentiane</VEE_Plant_Gentian.label>
  <VEE_Plant_Gentian.description>Une grande fleur cultivée avec des pétales bleus inimitables. Les gentianes sont magnifiques.</VEE_Plant_Gentian.description>

  <VEE_Plant_Petunia.label>pétunia</VEE_Plant_Petunia.label>
  <VEE_Plant_Petunia.description>Une fleur de longue durée aux pétales violets. Les pétunias sont très belles.</VEE_Plant_Petunia.description>


</LanguageData>