<?xml version="1.0" encoding="UTF-8"?>
<LanguageData>
<VEF_GeneralTitle>Général</VEF_GeneralTitle>
    <!-- CSG -->
<CSGTitle>Génération de structure personnalisée</CSGTitle>
<CSGLog>Activer le journal de débogage de génération de structure: </CSGLog>

    <!-- Toggable patches -->
<VEF_TPTitle>Patchs adaptables</VEF_TPTitle>
<NeedRestart>Tous les paramètres nécessitent un redémarrage pour être appliqués.</NeedRestart>
<XPatchFound>{0} correctifs trouvés</XPatchFound>

	<!-- Weather damages -->
<VEF.WeatherDamages>Dégâts climatiques</VEF.WeatherDamages>
<VEF.EnableWeatherDamage>{0} </VEF.EnableWeatherDamage>
    <!-- Faction Discovery -->
<FDTitle>Découverte de faction</FDTitle>
<NeedToBeInGame>Vous devez d'abord charger une sauvegarde.</NeedToBeInGame>
<AskForPopUp>Ajouter faction</AskForPopUp>
<AskForPopUpExplained>Cliquer sur ce bouton afin que l'on vous demande pour chaque faction si vous voulez les ajouter à votre jeu.</AskForPopUpExplained>
<CanAddXFaction>{0} faction{0_multiple ? s : } {0_multiple ? peuvent : peut } être ajouté à votre sauvegarde actuelle.</CanAddXFaction>

<VEF.DisableModSourceReport>Désactiver l'origine du mod dans la fiche d'information</VEF.DisableModSourceReport>

<VEF.Shields.Search>Chercher</VEF.Shields.Search>
<VEF.Shields.ResetModSettingsToDefault>Paramètres par défaut du mod</VEF.Shields.ResetModSettingsToDefault>
<VEF.Shields.ExplanationTitle>Configurer les armes pour qu'elles soient utilisables ou non avec des boucliers.</VEF.Shields.ExplanationTitle>
<VEF.Shields.ShowMeleeWeapons>Armes de mêlée</VEF.Shields.ShowMeleeWeapons>
<VEF.Shields.ShowRangeWeapons>Armes à distance</VEF.Shields.ShowRangeWeapons>

<VEF_DisableTextureCaching>Désactiver la mise en cache des textures</VEF_DisableTextureCaching>
<VEF_EnablePipeSystemNoStorageAlert>Activer l'alerte de stockage du système de tuyauterie</VEF_EnablePipeSystemNoStorageAlert>
<VEF_FactionDiscovery>Découverte de factions :</VEF_FactionDiscovery>
<VEF_CustomStructureGeneration>Génération de structures personnalisées :</VEF_CustomStructureGeneration>
<VEF_TextureVariations>Variations des textures :</VEF_TextureVariations>
<VEF_VerboseLogging>Journal verbeux</VEF_VerboseLogging>
<VEF_UnforbidMinedOres>Autoriser les minerais extraits</VEF_UnforbidMinedOres>
<VEF_Never>— Jamais</VEF_Never>
<VEF_HomeArea>— Zone de base</VEF_HomeArea>
<VEF_Always>— Toujours</VEF_Always>
<VEF_NeverDesc>Ne jamais Autoriser les minerais extraits (c'est ainsi que le jeu de base fonctionne pour les colons non humains, tels que les animaux et les mécanoïdes).</VEF_NeverDesc>
<VEF_HomeAreaDesc>Autoriser les minerais extraits par les colons s'ils sont extraits dans la Zone de base.</VEF_HomeAreaDesc>
<VEF_AlwaysDesc>Toujours Autoriser les minerais extraits par les colons.</VEF_AlwaysDesc>


</LanguageData>