<?xml version="1.0" encoding="utf-8"?>
<LanguageData>

<VBE_DalgonaCoffeeHigh.stages.Sugary_awakening.label>Réveil sucré</VBE_DalgonaCoffeeHigh.stages.Sugary_awakening.label>
<VBE_DalgonaCoffeeHigh.stages.Sugary_awakening.description>Ce café dalgona a fait du bien, maintenant allons travailler.</VBE_DalgonaCoffeeHigh.stages.Sugary_awakening.description>

<VBE_DrankMasalaChai.stages.Fancied_a_zesty_cuppa.label>Une tasse de thé épicée</VBE_DrankMasalaChai.stages.Fancied_a_zesty_cuppa.label>
<VBE_DrankMasalaChai.stages.Fancied_a_zesty_cuppa.description>Une tasse de masala chai épicé délicieuse et complexe illumine vraiment ma journée.</VBE_DrankMasalaChai.stages.Fancied_a_zesty_cuppa.description>

<VBE_MintCoffeeHigh.stages.Fresh_awakening.label>Réveil frais</VBE_MintCoffeeHigh.stages.Fresh_awakening.label>
<VBE_MintCoffeeHigh.stages.Fresh_awakening.description>Ce café à la menthe a fait du bien, maintenant allons travailler.</VBE_MintCoffeeHigh.stages.Fresh_awakening.description>

<VBE_DrankMintTea.stages.Refreshing_tea.label>Thé rafraîchissant</VBE_DrankMintTea.stages.Refreshing_tea.label>
<VBE_DrankMintTea.stages.Refreshing_tea.description>Une tasse de thé à la menthe délicieusement fraîche illumine vraiment ma journée.</VBE_DrankMintTea.stages.Refreshing_tea.description>

<VBE_DrankNoonChai.stages.Fancied_a_salty_cuppa.label>Une tasse de thé salé</VBE_DrankNoonChai.stages.Fancied_a_salty_cuppa.label>
<VBE_DrankNoonChai.stages.Fancied_a_salty_cuppa.description>Une tasse de chaï de midi délicieuse illumine vraiment ma journée.</VBE_DrankNoonChai.stages.Fancied_a_salty_cuppa.description>

<VCE_ConsumedMintLeaves.stages.consumed_mint.label>menthe consommée</VCE_ConsumedMintLeaves.stages.consumed_mint.label>
<VCE_ConsumedMintLeaves.stages.consumed_mint.description>Une haleine fraîche !</VCE_ConsumedMintLeaves.stages.consumed_mint.description>


</LanguageData>