<?xml version="1.0" encoding="utf-8"?>
<LanguageData>

<VPE_Bliss.stages.bliss-0.label>félicité</VPE_Bliss.stages.bliss-0.label>
<VPE_Bliss.stages.bliss-0.description>Peut-être que ce n'est pas si mal.</VPE_Bliss.stages.bliss-0.description>
<VPE_Bliss.stages.bliss-1.label>félicité</VPE_Bliss.stages.bliss-1.label>
<VPE_Bliss.stages.bliss-1.description>Je pense que les choses s'améliorent.</VPE_Bliss.stages.bliss-1.description>
<VPE_Bliss.stages.bliss-2.label>félicité</VPE_Bliss.stages.bliss-2.label>
<VPE_Bliss.stages.bliss-2.description>Tout s'améliore, lentement mais sûrement.</VPE_Bliss.stages.bliss-2.description>
<VPE_Bliss.stages.bliss-3.label>félicité</VPE_Bliss.stages.bliss-3.label>
<VPE_Bliss.stages.bliss-3.description>Je me sens bien en ce moment, les choses s'améliorent.</VPE_Bliss.stages.bliss-3.description>
<VPE_Bliss.stages.bliss-4.label>félicité</VPE_Bliss.stages.bliss-4.label>
<VPE_Bliss.stages.bliss-4.description>Je me sens chaud et confus, le simple fait d'être en vie me fait du bien.</VPE_Bliss.stages.bliss-4.description>
<VPE_Bliss.stages.bliss-5.label>félicité</VPE_Bliss.stages.bliss-5.label>
<VPE_Bliss.stages.bliss-5.description>Je suis sur le point d'exploser d'excitation. J'aime cette colonie, j'aime ce monde et toutes les vies qu'il abrite.</VPE_Bliss.stages.bliss-5.description>
<VPE_Bliss.stages.bliss-6.label>félicité</VPE_Bliss.stages.bliss-6.label>
<VPE_Bliss.stages.bliss-6.description>Toutes les couleurs de ce monde sont si vives, les sons sont si tranquilles, l'air est si vivifiant. Cette vie me laisse sans voix.</VPE_Bliss.stages.bliss-6.description>
<VPE_Bliss.stages.bliss-7.label>félicité</VPE_Bliss.stages.bliss-7.label>
<VPE_Bliss.stages.bliss-7.description>Ça y est, n'est-ce pas ? J'ai vraiment atteint le nirvana lui-même. La vie elle-même est l'incarnation même du bonheur.</VPE_Bliss.stages.bliss-7.description>

<VPE_MindWiped.stages.mind_wiped.label>esprit effacé</VPE_MindWiped.stages.mind_wiped.label>
<VPE_MindWiped.stages.mind_wiped.description>Je ne me souviens de rien, je découvre tout à nouveau !</VPE_MindWiped.stages.mind_wiped.description>

<VPE_TimeQuake.stages.time_quake.label>séisme temporel</VPE_TimeQuake.stages.time_quake.label>
<VPE_TimeQuake.stages.time_quake.description>Tous ceux que je connaissais ont tellement changé. Ce séisme temporel a vraiment fait quelque chose sur moi.</VPE_TimeQuake.stages.time_quake.description>

<VPE_Future.stages.I_know_my_future.label>Je connais mon avenir !</VPE_Future.stages.I_know_my_future.label>
<VPE_Future.stages.I_know_my_future.description>Je connais mon avenir, et les choses se présentent bien !</VPE_Future.stages.I_know_my_future.description>

<VPE_Thrall.stages.Thrall.label>Thrall</VPE_Thrall.stages.Thrall.label>
<VPE_Thrall.stages.Thrall.description>Ughhh ugghhh aaaahhhh</VPE_Thrall.stages.Thrall.description>


</LanguageData>