<?xml version="1.0" encoding="utf-8"?>
<LanguageData>

<VCE_VegMilkExtractor.label>extracteur de lait végétal</VCE_VegMilkExtractor.label>
<VCE_VegMilkExtractor.description>Un petit poste de travail contenant une presse, une centrifugeuse et une décanteuse industrielle pour séparer l'extrait végétal du moût. Les forces G élevées générées par la centrifugeuse permettent d'extraire le lait végétal du riz, des amandes, des noix de coco, de l'avoine et du soja.</VCE_VegMilkExtractor.description>

<VCE_RawOats.label>avoine</VCE_RawOats.label>
<VCE_RawOats.description>Grain de la plante d'avoine. L'avoine a de nombreuses utilisations dans l'alimentation ; le plus souvent, elle est roulée ou écrasée en farine d'avoine. Les flocons d'avoine sont principalement consommés sous forme de bouillie, mais peuvent également être utilisés dans une variété de produits de boulangerie. L'avoine est également utilisée pour la production de substituts du lait.</VCE_RawOats.description>


<VCE_Oats.label>avoine</VCE_Oats.label>
<VCE_Oats.description>L'avoine, parfois appelée avoine commune, est une espèce de céréale cultivée pour sa graine, qui porte le même nom. L'avoine a de nombreux usages en gastronomie, et elle peut également être transformée en lait végétal.\n\n&lt;color=#E5E54C&gt;Effet de jeu :&lt;/color&gt; L'avoine a un faible rendement, mais elle est très polyvalente, étant une "double culture", dans le sens où elle produit à la fois de la farine et de l'avoine qui peut être utilisée comme légume ou transformée en lait.</VCE_Oats.description>


</LanguageData>