<?xml version="1.0" encoding="utf-8"?>
<LanguageData>

<Hunter.label>chasseur</Hunter.label>
<Hunter.labelFemale>chasseuse</Hunter.labelFemale>
<Hunter.labelMale>chasseur</Hunter.labelMale>
<Hunter.labelPlural>chasseurs</Hunter.labelPlural>
<Hunter.labelFemalePlural>chasseuses</Hunter.labelFemalePlural>

<VEE_TribalHunter.label>chasseur</VEE_TribalHunter.label>
<VEE_TribalHunter.labelFemale>chasseuse</VEE_TribalHunter.labelFemale>
<VEE_TribalHunter.labelMale>chasseur</VEE_TribalHunter.labelMale>
<VEE_TribalHunter.labelPlural>chasseurs</VEE_TribalHunter.labelPlural>
<VEE_TribalHunter.labelFemalePlural>chasseuses</VEE_TribalHunter.labelFemalePlural>


</LanguageData>