<?xml version="1.0" encoding="utf-8"?>
<LanguageData>

<VFE_FactoryFloor.label>sol d'usine</VFE_FactoryFloor.label>
<VFE_FactoryFloor.description>Des tôles d'acier renforcées, capables de maintenir en place des machines lourdes et complexes. Ce n'est pas très joli à regarder.</VFE_FactoryFloor.description>

<VFE_FactoryPath.label>passage d'usine</VFE_FactoryPath.label>
<VFE_FactoryPath.description>Un passage désigné et sûr pour traverser l'usine. Augmente la vitesse de déplacement, mais doit être placé sur le sol d'usine.</VFE_FactoryPath.description>


</LanguageData>